odoo/addons/project_task_parent_due_auto/README.rst
odoo/addons/project_task_parent_due_auto/__init__.py
odoo/addons/project_task_parent_due_auto/__manifest__.py
odoo/addons/project_task_parent_due_auto/i18n/it.po
odoo/addons/project_task_parent_due_auto/i18n/project_task_parent_due_auto.pot
odoo/addons/project_task_parent_due_auto/i18n/pt_BR.po
odoo/addons/project_task_parent_due_auto/models/__init__.py
odoo/addons/project_task_parent_due_auto/models/project_task.py
odoo/addons/project_task_parent_due_auto/readme/CONTRIBUTORS.md
odoo/addons/project_task_parent_due_auto/readme/DESCRIPTION.md
odoo/addons/project_task_parent_due_auto/static/description/icon.png
odoo/addons/project_task_parent_due_auto/static/description/index.html
odoo/addons/project_task_parent_due_auto/tests/__init__.py
odoo/addons/project_task_parent_due_auto/tests/test_parent_due_auto.py
odoo_addon_project_task_parent_due_auto-18.0.1.0.1.dist-info/METADATA
odoo_addon_project_task_parent_due_auto-18.0.1.0.1.dist-info/WHEEL
odoo_addon_project_task_parent_due_auto-18.0.1.0.1.dist-info/top_level.txt
odoo_addon_project_task_parent_due_auto-18.0.1.0.1.dist-info/RECORD
